calculator_gabija/__init__.py
calculator_gabija/calculator_main.py
calculator_gabija/calculator_session.py
calculator_gabija-1.0.0.dist-info/LICENSE.txt
calculator_gabija-1.0.0.dist-info/METADATA
calculator_gabija-1.0.0.dist-info/WHEEL
calculator_gabija-1.0.0.dist-info/top_level.txt
calculator_gabija-1.0.0.dist-info/RECORD
